environ_loader/__init__.py
environ_loader/__main__.py
environ_loader/expand.py
environ_loader/linux.py
environ_loader/loader.py
environ_loader/var_list.py
environ_loader/windows.py
environ_loader-0.0.2.dist-info/entry_points.txt
environ_loader-0.0.2.dist-info/LICENSE
environ_loader-0.0.2.dist-info/WHEEL
environ_loader-0.0.2.dist-info/METADATA
environ_loader-0.0.2.dist-info/RECORD
