Metadata-Version: 2.1
Name: environ-loader
Version: 0.0.2
Summary: Environ Loader
Home-page: https://github.com/CD3/environ-loader
License: MIT
Author: CD Clark III
Author-email: clifton.clark@gmail.com
Requires-Python: >=3.7,<4.0
Classifier: Development Status :: 3 - Alpha
Classifier: License :: OSI Approved :: MIT License
Classifier: Programming Language :: Python :: 3
Classifier: Programming Language :: Python :: 3.10
Classifier: Programming Language :: Python :: 3.7
Classifier: Programming Language :: Python :: 3.8
Classifier: Programming Language :: Python :: 3.9
Requires-Dist: click (>=8.0.1)
Project-URL: Changelog, https://github.com/CD3/environ-loader/releases
Project-URL: Documentation, https://environ-loader.readthedocs.io
Project-URL: Repository, https://github.com/CD3/environ-loader
